{
"gameId": 273242415,
"plays": [],
"winprobability": [],
"boxscore": {
"teams": [
{
"team": {
"shortDisplayName": "American",
"uid": "s:40~l:41~t:44",
"alternateColor": "c8102e",
"color": "c41130",
"displayName": "American Eagles",
"name": "Eagles",
"logo": "https://a.espncdn.com/i/teamlogos/ncaa/500/44.png",
"location": "American",
"id": "44",
"abbreviation": "AMER",
"slug": "american-eagles"
},
"statistics": [
{
"displayValue": "18-56",
"name": "fieldGoalsMade-fieldGoalsAttempted",
"label": "FG"
},
{
"displayValue": "32.1",
"name": "fieldGoalPct",
"label": "Field Goal %",
"abbreviation": "FG%"
},
{
"displayValue": "6-19",
"name": "threePointFieldGoalsMade-threePointFieldGoalsAttempted",
"label": "3PT"
},
{
"displayValue": "31.6",
"name": "threePointFieldGoalPct",
"label": "Three Point %",
"abbreviation": "3P%"
},
{
"displayValue": "12-17",
"name": "freeThrowsMade-freeThrowsAttempted",
"label": "FT"
},
{
"displayValue": "70.6",
"name": "freeThrowPct",
"label": "Free Throw %",
"abbreviation": "FT%"
},
{
"displayValue": "41",
"name": "totalRebounds",
"label": "Rebounds",
"abbreviation": "REB"
},
{
"displayValue": "13",
"name": "offensiveRebounds",
"label": "Offensive Rebounds",
"abbreviation": "OR"
},
{
"displayValue": "22",
"name": "defensiveRebounds",
"label": "Defensive Rebounds",
"abbreviation": "DR"
},
{
"displayValue": "6",
"name": "teamRebounds",
"label": "Team Rebounds",
"abbreviation": "TREB"
},
{
"displayValue": "5",
"name": "assists",
"label": "Assists",
"abbreviation": "AST"
},
{
"displayValue": "3",
"name": "steals",
"label": "Steals",
"abbreviation": "STL"
},
{
"displayValue": "0",
"name": "blocks",
"label": "Blocks",
"abbreviation": "BLK"
},
{
"displayValue": "9",
"name": "turnovers",
"label": "Turnovers",
"abbreviation": "TO"
},
{
"displayValue": "0",
"name": "teamTurnovers",
"label": "Team Turnovers",
"abbreviation": "TTO"
},
{
"displayValue": "9",
"name": "totalTurnovers",
"label": "Total Turnovers",
"abbreviation": "ToTO"
},
{
"displayValue": "0",
"name": "technicalFouls",
"label": "Technical Fouls",
"abbreviation": "TECH"
},
{
"displayValue": "0",
"name": "totalTechnicalFouls",
"label": "Total Technical Fouls",
"abbreviation": "TECH"
},
{
"displayValue": "0",
"name": "flagrantFouls",
"label": "Flagrant Fouls",
"abbreviation": "FLAG"
},
{
"displayValue": "16",
"name": "fouls",
"label": "Fouls",
"abbreviation": "PF"
},
{
"displayValue": "0",
"name": "largestLead",
"label": "Largest Lead",
"abbreviation": "LL"
}
]
},
{
"team": {
"shortDisplayName": "Morgan State",
"uid": "s:40~l:41~t:2415",
"alternateColor": "f47937",
"color": "014786",
"displayName": "Morgan St Bears",
"name": "Bears",
"logo": "https://a.espncdn.com/i/teamlogos/ncaa/500/2415.png",
"location": "Morgan St",
"id": "2415",
"abbreviation": "MORG",
"slug": "morgan-st-bears"
},
"statistics": [
{
"displayValue": "24-48",
"name": "fieldGoalsMade-fieldGoalsAttempted",
"label": "FG"
},
{
"displayValue": "50.0",
"name": "fieldGoalPct",
"label": "Field Goal %",
"abbreviation": "FG%"
},
{
"displayValue": "4-9",
"name": "threePointFieldGoalsMade-threePointFieldGoalsAttempted",
"label": "3PT"
},
{
"displayValue": "44.4",
"name": "threePointFieldGoalPct",
"label": "Three Point %",
"abbreviation": "3P%"
},
{
"displayValue": "10-18",
"name": "freeThrowsMade-freeThrowsAttempted",
"label": "FT"
},
{
"displayValue": "55.6",
"name": "freeThrowPct",
"label": "Free Throw %",
"abbreviation": "FT%"
},
{
"displayValue": "38",
"name": "totalRebounds",
"label": "Rebounds",
"abbreviation": "REB"
},
{
"displayValue": "8",
"name": "offensiveRebounds",
"label": "Offensive Rebounds",
"abbreviation": "OR"
},
{
"displayValue": "27",
"name": "defensiveRebounds",
"label": "Defensive Rebounds",
"abbreviation": "DR"
},
{
"displayValue": "3",
"name": "teamRebounds",
"label": "Team Rebounds",
"abbreviation": "TREB"
},
{
"displayValue": "9",
"name": "assists",
"label": "Assists",
"abbreviation": "AST"
},
{
"displayValue": "3",
"name": "steals",
"label": "Steals",
"abbreviation": "STL"
},
{
"displayValue": "12",
"name": "blocks",
"label": "Blocks",
"abbreviation": "BLK"
},
{
"displayValue": "11",
"name": "turnovers",
"label": "Turnovers",
"abbreviation": "TO"
},
{
"displayValue": "0",
"name": "teamTurnovers",
"label": "Team Turnovers",
"abbreviation": "TTO"
},
{
"displayValue": "11",
"name": "totalTurnovers",
"label": "Total Turnovers",
"abbreviation": "ToTO"
},
{
"displayValue": "0",
"name": "technicalFouls",
"label": "Technical Fouls",
"abbreviation": "TECH"
},
{
"displayValue": "0",
"name": "totalTechnicalFouls",
"label": "Total Technical Fouls",
"abbreviation": "TECH"
},
{
"displayValue": "0",
"name": "flagrantFouls",
"label": "Flagrant Fouls",
"abbreviation": "FLAG"
},
{
"displayValue": "16",
"name": "fouls",
"label": "Fouls",
"abbreviation": "PF"
},
{
"displayValue": "8",
"name": "largestLead",
"label": "Largest Lead",
"abbreviation": "LL"
}
]
}
],
"players": [
{
"team": {
"shortDisplayName": "American",
"uid": "s:40~l:41~t:44",
"alternateColor": "c8102e",
"color": "c41130",
"displayName": "American Eagles",
"name": "Eagles",
"logo": "https://a.espncdn.com/i/teamlogos/ncaa/500/44.png",
"location": "American",
"id": "44",
"abbreviation": "AMER",
"slug": "american-eagles"
},
"statistics": [
{
"names": [
"MIN",
"FG",
"3PT",
"FT",
"OREB",
"DREB",
"REB",
"AST",
"STL",
"BLK",
"TO",
"PF",
"PTS"
],
"athletes": [
{
"starter": false,
"athlete": {
"uid": "s:40~l:41~a:36858",
"displayName": "Bryce Simon",
"jersey": "33 ",
"guid": "351ccd9061b467879dc773a8625efdfe",
"links": [
{
"href": "https://www.espn.com/mens-college-basketball/player/_/id/36858/bryce-simon",
"text": "Player Card"
},
{
"href": "http://www.espn.com/mens-college-basketball/player/stats/_/id/36858/bryce-simon",
"text": "Stats"
},
{
"href": "http://www.espn.com/mens-college-basketball/player/splits/_/id/36858/bryce-simon",
"text": "Splits"
},
{
"href": "http://www.espn.com/mens-college-basketball/player/gamelog/_/id/36858/bryce-simon",
"text": "Game Log"
},
{
"href": "http://www.espn.com/mens-college-basketball/player/news/_/id/36858/bryce-simon",
"text": "News"
},
{
"href": "http://www.espn.com/mens-college-basketball/player/bio/_/id/36858/bryce-simon",
"text": "Bio"
},
{
"href": "http://www.espn.com/mens-college-basketball/player/_/id/36858/bryce-simon",
"text": "Overview"
}
],
"id": "36858",
"position": {
"displayName": "Forward",
"name": "Forward",
"abbreviation": "F"
},
"shortName": "B. Simon"
},
"ejected": false,
"stats": [
"20",
"0-6",
"0-2",
"0-2",
"1",
"1",
"2",
"0",
"2",
"0",
"0",
"0",
"0"
],
"didNotPlay": false,
"active": false
},
{
"starter": false,
"athlete": {
"uid": "s:40~l:41~a:27810",
"displayName": "Jordan Nichols",
"jersey": "44 ",
"guid": "0d84619bd4d9e297b6e6cd997870674c",
"links": [
{
"href": "https://www.espn.com/mens-college-basketball/player/_/id/27810/jordan-nichols",
"text": "Player Card"
},
{
"href": "http://www.espn.com/mens-college-basketball/player/stats/_/id/27810/jordan-nichols",
"text": "Stats"
},
{
"href": "http://www.espn.com/mens-college-basketball/player/splits/_/id/27810/jordan-nichols",
"text": "Splits"
},
{
"href": "http://www.espn.com/mens-college-basketball/player/gamelog/_/id/27810/jordan-nichols",
"text": "Game Log"
},
{
"href": "http://www.espn.com/mens-college-basketball/player/news/_/id/27810/jordan-nichols",
"text": "News"
},
{
"href": "http://www.espn.com/mens-college-basketball/player/bio/_/id/27810/jordan-nichols",
"text": "Bio"
},
{
"href": "http://www.espn.com/mens-college-basketball/player/_/id/27810/jordan-nichols",
"text": "Overview"
}
],
"id": "27810",
"position": {
"displayName": "Forward",
"name": "Forward",
"abbreviation": "F"
},
"shortName": "J. Nichols"
},
"ejected": false,
"stats": [
"19",
"2-3",
"0-0",
"0-0",
"4",
"3",
"7",
"0",
"0",
"0",
"1",
"4",
"4"
],
"didNotPlay": false,
"active": false
},
{
"starter": false,
"athlete": {
"uid": "s:40~l:41~a:27808",
"displayName": "Brian Gilmore",
"jersey": "14 ",
"guid": "c3f7a468672adde2e5ce98d26197adea",
"links": [
{
"href": "https://www.espn.com/mens-college-basketball/player/_/id/27808/brian-gilmore",
"text": "Player Card"
},
{
"href": "http://www.espn.com/mens-college-basketball/player/stats/_/id/27808/brian-gilmore",
"text": "Stats"
},
{
"href": "http://www.espn.com/mens-college-basketball/player/splits/_/id/27808/brian-gilmore",
"text": "Splits"
},
{
"href": "http://www.espn.com/mens-college-basketball/player/gamelog/_/id/27808/brian-gilmore",
"text": "Game Log"
},
{
"href": "http://www.espn.com/mens-college-basketball/player/news/_/id/27808/brian-gilmore",
"text": "News"
},
{
"href": "http://www.espn.com/mens-college-basketball/player/bio/_/id/27808/brian-gilmore",
"text": "Bio"
},
{
"href": "http://www.espn.com/mens-college-basketball/player/_/id/27808/brian-gilmore",
"text": "Overview"
}
],
"id": "27808",
"position": {
"displayName": "Forward",
"name": "Forward",
"abbreviation": "F"
},
"shortName": "B. Gilmore"
},
"ejected": false,
"stats": [
"17",
"0-6",
"0-4",
"1-2",
"2",
"2",
"4",
"1",
"0",
"0",
"1",
"1",
"1"
],
"didNotPlay": false,
"active": false
},
{
"starter": false,
"athlete": {
"uid": "s:40~l:41~a:22947",
"displayName": "Travis Lay",
"jersey": "34 ",
"guid": "7f2a8783e47487bea84cdbc174f0c095",
"links": [
{
"href": "https://www.espn.com/mens-college-basketball/player/_/id/22947/travis-lay",
"text": "Player Card"
},
{
"href": "http://www.espn.com/mens-college-basketball/player/stats/_/id/22947/travis-lay",
"text": "Stats"
},
{
"href": "http://www.espn.com/mens-college-basketball/player/splits/_/id/22947/travis-lay",
"text": "Splits"
},
{
"href": "http://www.espn.com/mens-college-basketball/player/gamelog/_/id/22947/travis-lay",
"text": "Game Log"
},
{
"href": "http://www.espn.com/mens-college-basketball/player/news/_/id/22947/travis-lay",
"text": "News"
},
{
"href": "http://www.espn.com/mens-college-basketball/player/bio/_/id/22947/travis-lay",
"text": "Bio"
},
{
"href": "http://www.espn.com/mens-college-basketball/player/_/id/22947/travis-lay",
"text": "Overview"
}
],
"id": "22947",
"position": {
"displayName": "Forward",
"name": "Forward",
"abbreviation": "F"
},
"shortName": "T. Lay"
},
"ejected": false,
"stats": [
"29",
"3-6",
"0-1",
"1-1",
"1",
"5",
"6",
"0",
"1",
"0",
"1",
"0",
"7"
],
"didNotPlay": false,
"active": false
},
{
"starter": false,
"athlete": {
"uid": "s:40~l:41~a:36857",
"displayName": "Constantin Motnii",
"guid": "ee08379de214d02ac0894d3cefdf5a3b",
"links": [
{
"href": "https://www.espn.com/mens-college-basketball/player/_/id/36857/constantin-motnii",
"text": "Player Card"
},
{
"href": "http://www.espn.com/mens-college-basketball/player/splits/_/id/36857/constantin-motnii",
"text": "Splits"
},
{
"href": "http://www.espn.com/mens-college-basketball/player/gamelog/_/id/36857/constantin-motnii",
"text": "Game Log"
},
{
"href": "http://www.espn.com/mens-college-basketball/player/news/_/id/36857/constantin-motnii",
"text": "News"
},
{
"href": "http://www.espn.com/mens-college-basketball/player/bio/_/id/36857/constantin-motnii",
"text": "Bio"
},
{
"href": "http://www.espn.com/mens-college-basketball/player/_/id/36857/constantin-motnii",
"text": "Overview"
}
],
"id": "36857",
"position": {
"displayName": "Center",
"name": "Center",
"abbreviation": "C"
},
"shortName": "C. Motnii"
},
"ejected": false,
"stats": [
"15",
"1-2",
"0-0",
"0-0",
"1",
"3",
"4",
"1",
"0",
"0",
"4",
"1",
"2"
],
"didNotPlay": false,
"active": false
},
{
"starter": false,
"athlete": {
"uid": "s:40~l:41~a:22424",
"displayName": "Cornelio Guibunda",
"jersey": "32 ",
"guid": "9ce835ff9406c953c47ac47662e9c661",
"links": [
{
"href": "https://www.espn.com/mens-college-basketball/player/_/id/22424/cornelio-guibunda",
"text": "Player Card"
},
{
"href": "http://www.espn.com/mens-college-basketball/player/stats/_/id/22424/cornelio-guibunda",
"text": "Stats"
},
{
"href": "http://www.espn.com/mens-college-basketball/player/splits/_/id/22424/cornelio-guibunda",
"text": "Splits"
},
{
"href": "http://www.espn.com/mens-college-basketball/player/gamelog/_/id/22424/cornelio-guibunda",
"text": "Game Log"
},
{
"href": "http://www.espn.com/mens-college-basketball/player/news/_/id/22424/cornelio-guibunda",
"text": "News"
},
{
"href": "http://www.espn.com/mens-college-basketball/player/bio/_/id/22424/cornelio-guibunda",
"text": "Bio"
},
{
"href": "http://www.espn.com/mens-college-basketball/player/_/id/22424/cornelio-guibunda",
"text": "Overview"
}
],
"id": "22424",
"position": {
"displayName": "Center",
"name": "Center",
"abbreviation": "C"
},
"shortName": "C. Guibunda"
},
"ejected": false,
"stats": [
"6",
"0-0",
"0-0",
"0-0",
"0",
"2",
"2",
"0",
"0",
"0",
"0",
"0",
"0"
],
"didNotPlay": false,
"active": false
},
{
"starter": false,
"athlete": {
"uid": "s:40~l:41~a:36854",
"displayName": "Frank Borden",
"jersey": "15 ",
"guid": "b24a363ad8c0e795ef74b53d6d7b4aa5",
"links": [
{
"href": "https://www.espn.com/mens-college-basketball/player/_/id/36854/frank-borden",
"text": "Player Card"
},
{
"href": "http://www.espn.com/mens-college-basketball/player/stats/_/id/36854/frank-borden",
"text": "Stats"
},
{
"href": "http://www.espn.com/mens-college-basketball/player/splits/_/id/36854/frank-borden",
"text": "Splits"
},
{
"href": "http://www.espn.com/mens-college-basketball/player/gamelog/_/id/36854/frank-borden",
"text": "Game Log"
},
{
"href": "http://www.espn.com/mens-college-basketball/player/news/_/id/36854/frank-borden",
"text": "News"
},
{
"href": "http://www.espn.com/mens-college-basketball/player/bio/_/id/36854/frank-borden",
"text": "Bio"
},
{
"href": "http://www.espn.com/mens-college-basketball/player/_/id/36854/frank-borden",
"text": "Overview"
}
],
"id": "36854",
"position": {
"displayName": "Guard",
"name": "Guard",
"abbreviation": "G"
},
"shortName": "F. Borden"
},
"ejected": false,
"stats": [
"26",
"1-4",
"1-1",
"4-4",
"0",
"2",
"2",
"0",
"0",
"0",
"0",
"4",
"7"
],
"didNotPlay": false,
"active": false
},
{
"starter": false,
"athlete": {
"uid": "s:40~l:41~a:27809",
"displayName": "Derrick Mercer",
"jersey": "3  ",
"guid": "f572e45b5bf98e42d2e482b3090b3a3b",
"links": [
{
"href": "https://www.espn.com/mens-college-basketball/player/_/id/27809/derrick-mercer",
"text": "Player Card"
},
{
"href": "http://www.espn.com/mens-college-basketball/player/stats/_/id/27809/derrick-mercer",
"text": "Stats"
},
{
"href": "http://www.espn.com/mens-college-basketball/player/splits/_/id/27809/derrick-mercer",
"text": "Splits"
},
{
"href": "http://www.espn.com/mens-college-basketball/player/gamelog/_/id/27809/derrick-mercer",
"text": "Game Log"
},
{
"href": "http://www.espn.com/mens-college-basketball/player/news/_/id/27809/derrick-mercer",
"text": "News"
},
{
"href": "http://www.espn.com/mens-college-basketball/player/bio/_/id/27809/derrick-mercer",
"text": "Bio"
},
{
"href": "http://www.espn.com/mens-college-basketball/player/_/id/27809/derrick-mercer",
"text": "Overview"
}
],
"id": "27809",
"position": {
"displayName": "Guard",
"name": "Guard",
"abbreviation": "G"
},
"shortName": "D. Mercer"
},
"ejected": false,
"stats": [
"36",
"6-14",
"1-3",
"0-2",
"0",
"1",
"1",
"3",
"0",
"0",
"1",
"5",
"13"
],
"didNotPlay": false,
"active": false
},
{
"starter": false,
"athlete": {
"uid": "s:40~l:41~a:27806",
"displayName": "Garrison Carr",
"jersey": "5  ",
"guid": "0c6d3f611e8e5903026a8028285ddb08",
"links": [
{
"href": "https://www.espn.com/mens-college-basketball/player/_/id/27806/garrison-carr",
"text": "Player Card"
},
{
"href": "http://www.espn.com/mens-college-basketball/player/stats/_/id/27806/garrison-carr",
"text": "Stats"
},
{
"href": "http://www.espn.com/mens-college-basketball/player/splits/_/id/27806/garrison-carr",
"text": "Splits"
},
{
"href": "http://www.espn.com/mens-college-basketball/player/gamelog/_/id/27806/garrison-carr",
"text": "Game Log"
},
{
"href": "http://www.espn.com/mens-college-basketball/player/news/_/id/27806/garrison-carr",
"text": "News"
},
{
"href": "http://www.espn.com/mens-college-basketball/player/bio/_/id/27806/garrison-carr",
"text": "Bio"
},
{
"href": "http://www.espn.com/mens-college-basketball/player/_/id/27806/garrison-carr",
"text": "Overview"
}
],
"id": "27806",
"position": {
"displayName": "Guard",
"name": "Guard",
"abbreviation": "G"
},
"shortName": "G. Carr"
},
"ejected": false,
"stats": [
"24",
"4-14",
"4-8",
"6-6",
"1",
"0",
"1",
"0",
"0",
"0",
"1",
"1",
"18"
],
"didNotPlay": false,
"active": false
},
{
"starter": false,
"athlete": {
"uid": "s:40~l:41~a:18741",
"displayName": "Romone Penny",
"jersey": "25 ",
"guid": "5d1695e4fd6b5380e7db6eefeae1f4ad",
"links": [
{
"href": "https://www.espn.com/mens-college-basketball/player/_/id/18741/romone-penny",
"text": "Player Card"
},
{
"href": "http://www.espn.com/mens-college-basketball/player/stats/_/id/18741/romone-penny",
"text": "Stats"
},
{
"href": "http://www.espn.com/mens-college-basketball/player/splits/_/id/18741/romone-penny",
"text": "Splits"
},
{
"href": "http://www.espn.com/mens-college-basketball/player/gamelog/_/id/18741/romone-penny",
"text": "Game Log"
},
{
"href": "http://www.espn.com/mens-college-basketball/player/news/_/id/18741/romone-penny",
"text": "News"
},
{
"href": "http://www.espn.com/mens-college-basketball/player/bio/_/id/18741/romone-penny",
"text": "Bio"
},
{
"href": "http://www.espn.com/mens-college-basketball/player/_/id/18741/romone-penny",
"text": "Overview"
}
],
"id": "18741",
"position": {
"displayName": "Guard",
"name": "Guard",
"abbreviation": "G"
},
"shortName": "R. Penny"
},
"ejected": false,
"stats": [
"8",
"1-1",
"0-0",
"0-0",
"0",
"0",
"0",
"0",
"0",
"0",
"0",
"0",
"2"
],
"didNotPlay": false,
"active": false
},
{
"starter": false,
"athlete": {
"uid": "s:40~l:41~a:27356",
"displayName": "Frane Markusovic",
"jersey": "4  ",
"guid": "db5b1e466c3ce17e1f945b6767ab4448",
"links": [
{
"href": "https://www.espn.com/mens-college-basketball/player/_/id/27356/frane-markusovic",
"text": "Player Card"
},
{
"href": "http://www.espn.com/mens-college-basketball/player/stats/_/id/27356/frane-markusovic",
"text": "Stats"
},
{
"href": "http://www.espn.com/mens-college-basketball/player/splits/_/id/27356/frane-markusovic",
"text": "Splits"
},
{
"href": "http://www.espn.com/mens-college-basketball/player/gamelog/_/id/27356/frane-markusovic",
"text": "Game Log"
},
{
"href": "http://www.espn.com/mens-college-basketball/player/news/_/id/27356/frane-markusovic",
"text": "News"
},
{
"href": "http://www.espn.com/mens-college-basketball/player/bio/_/id/27356/frane-markusovic",
"text": "Bio"
},
{
"href": "http://www.espn.com/mens-college-basketball/player/_/id/27356/frane-markusovic",
"text": "Overview"
}
],
"id": "27356",
"position": {
"displayName": "Center",
"name": "Center",
"abbreviation": "C"
},
"shortName": "F. Markusovic"
},
"ejected": false,
"stats": [],
"didNotPlay": true,
"active": false
},
{
"starter": false,
"athlete": {
"uid": "s:40~l:41~a:36856",
"displayName": "Steve Luptak",
"jersey": "22 ",
"guid": "662288b2a014538b97b8c8779e04ec5b",
"links": [
{
"href": "https://www.espn.com/mens-college-basketball/player/_/id/36856/steve-luptak",
"text": "Player Card"
},
{
"href": "http://www.espn.com/mens-college-basketball/player/stats/_/id/36856/steve-luptak",
"text": "Stats"
},
{
"href": "http://www.espn.com/mens-college-basketball/player/splits/_/id/36856/steve-luptak",
"text": "Splits"
},
{
"href": "http://www.espn.com/mens-college-basketball/player/gamelog/_/id/36856/steve-luptak",
"text": "Game Log"
},
{
"href": "http://www.espn.com/mens-college-basketball/player/news/_/id/36856/steve-luptak",
"text": "News"
},
{
"href": "http://www.espn.com/mens-college-basketball/player/bio/_/id/36856/steve-luptak",
"text": "Bio"
},
{
"href": "http://www.espn.com/mens-college-basketball/player/_/id/36856/steve-luptak",
"text": "Overview"
}
],
"id": "36856",
"position": {
"displayName": "Guard",
"name": "Guard",
"abbreviation": "G"
},
"shortName": "S. Luptak"
},
"ejected": false,
"stats": [],
"didNotPlay": true,
"active": false
},
{
"starter": false,
"athlete": {
"uid": "s:40~l:41~a:36855",
"displayName": "Nick Hendra",
"jersey": "21 ",
"guid": "c8552649a7eda2773d4594de33bd622f",
"links": [
{
"href": "https://www.espn.com/mens-college-basketball/player/_/id/36855/nick-hendra",
"text": "Player Card"
},
{
"href": "http://www.espn.com/mens-college-basketball/player/stats/_/id/36855/nick-hendra",
"text": "Stats"
},
{
"href": "http://www.espn.com/mens-college-basketball/player/splits/_/id/36855/nick-hendra",
"text": "Splits"
},
{
"href": "http://www.espn.com/mens-college-basketball/player/gamelog/_/id/36855/nick-hendra",
"text": "Game Log"
},
{
"href": "http://www.espn.com/mens-college-basketball/player/news/_/id/36855/nick-hendra",
"text": "News"
},
{
"href": "http://www.espn.com/mens-college-basketball/player/bio/_/id/36855/nick-hendra",
"text": "Bio"
},
{
"href": "http://www.espn.com/mens-college-basketball/player/_/id/36855/nick-hendra",
"text": "Overview"
}
],
"id": "36855",
"position": {
"displayName": "Guard",
"name": "Guard",
"abbreviation": "G"
},
"shortName": "N. Hendra"
},
"ejected": false,
"stats": [],
"didNotPlay": true,
"active": false
}
],
"totals": [
"",
"18-56",
"6-19",
"12-17",
"13",
"22",
"35",
"5",
"3",
"0",
"9",
"16",
"54"
],
"descriptions": [
"Minutes",
"Field Goals Made/Attempted",
"3-Point Field Goals Made/Attempted",
"Free Throws Made/Attempted",
"Offensive Rebounds",
"Defensive Rebounds",
"Rebounds",
"Assists",
"Steals",
"Blocks",
"Turnovers",
"Personal Fouls",
"Points"
],
"labels": [
"MIN",
"FG",
"3PT",
"FT",
"OREB",
"DREB",
"REB",
"AST",
"STL",
"BLK",
"TO",
"PF",
"PTS"
]
}
]
},
{
"team": {
"shortDisplayName": "Morgan State",
"uid": "s:40~l:41~t:2415",
"alternateColor": "f47937",
"color": "014786",
"displayName": "Morgan St Bears",
"name": "Bears",
"logo": "https://a.espncdn.com/i/teamlogos/ncaa/500/2415.png",
"location": "Morgan St",
"id": "2415",
"abbreviation": "MORG",
"slug": "morgan-st-bears"
},
"statistics": [
{
"names": [
"MIN",
"FG",
"3PT",
"FT",
"OREB",
"DREB",
"REB",
"AST",
"STL",
"BLK",
"TO",
"PF",
"PTS"
],
"athletes": [
{
"starter": false,
"athlete": {
"uid": "s:40~l:41~a:32476",
"displayName": "Chris Moore",
"jersey": "21 ",
"guid": "d9b6b4c06853b311b4ac3afbd1735f54",
"links": [
{
"href": "https://www.espn.com/mens-college-basketball/player/_/id/32476/chris-moore",
"text": "Player Card"
},
{
"href": "http://www.espn.com/mens-college-basketball/player/splits/_/id/32476/chris-moore",
"text": "Splits"
},
{
"href": "http://www.espn.com/mens-college-basketball/player/gamelog/_/id/32476/chris-moore",
"text": "Game Log"
},
{
"href": "http://www.espn.com/mens-college-basketball/player/news/_/id/32476/chris-moore",
"text": "News"
},
{
"href": "http://www.espn.com/mens-college-basketball/player/bio/_/id/32476/chris-moore",
"text": "Bio"
},
{
"href": "http://www.espn.com/mens-college-basketball/player/_/id/32476/chris-moore",
"text": "Overview"
}
],
"id": "32476",
"position": {
"displayName": "Forward",
"name": "Forward",
"abbreviation": "F"
},
"shortName": "C. Moore"
},
"ejected": false,
"stats": [
"17",
"3-3",
"0-0",
"0-0",
"2",
"2",
"4",
"0",
"0",
"1",
"1",
"3",
"6"
],
"didNotPlay": false,
"active": false
},
{
"starter": false,
"athlete": {
"uid": "s:40~l:41~a:32474",
"displayName": "Gilroy Hemsley",
"jersey": "44 ",
"guid": "da34e53dcf577718de554c57bbb88a23",
"links": [
{
"href": "https://www.espn.com/mens-college-basketball/player/_/id/32474/gilroy-hemsley",
"text": "Player Card"
},
{
"href": "http://www.espn.com/mens-college-basketball/player/stats/_/id/32474/gilroy-hemsley",
"text": "Stats"
},
{
"href": "http://www.espn.com/mens-college-basketball/player/splits/_/id/32474/gilroy-hemsley",
"text": "Splits"
},
{
"href": "http://www.espn.com/mens-college-basketball/player/gamelog/_/id/32474/gilroy-hemsley",
"text": "Game Log"
},
{
"href": "http://www.espn.com/mens-college-basketball/player/news/_/id/32474/gilroy-hemsley",
"text": "News"
},
{
"href": "http://www.espn.com/mens-college-basketball/player/bio/_/id/32474/gilroy-hemsley",
"text": "Bio"
},
{
"href": "http://www.espn.com/mens-college-basketball/player/_/id/32474/gilroy-hemsley",
"text": "Overview"
}
],
"id": "32474",
"position": {
"displayName": "Forward",
"name": "Forward",
"abbreviation": "F"
},
"shortName": "G. Hemsley"
},
"ejected": false,
"stats": [
"6",
"1-1",
"0-0",
"0-0",
"1",
"0",
"1",
"0",
"0",
"1",
"0",
"0",
"2"
],
"didNotPlay": false,
"active": false
},
{
"starter": false,
"athlete": {
"uid": "s:40~l:41~a:18247",
"displayName": "Marquise Kately",
"jersey": "32 ",
"guid": "b585398437b4fc52aa856e5dd0133fb9",
"links": [
{
"href": "https://www.espn.com/mens-college-basketball/player/_/id/18247/marquise-kately",
"text": "Player Card"
},
{
"href": "http://www.espn.com/mens-college-basketball/player/stats/_/id/18247/marquise-kately",
"text": "Stats"
},
{
"href": "http://www.espn.com/mens-college-basketball/player/splits/_/id/18247/marquise-kately",
"text": "Splits"
},
{
"href": "http://www.espn.com/mens-college-basketball/player/gamelog/_/id/18247/marquise-kately",
"text": "Game Log"
},
{
"href": "http://www.espn.com/mens-college-basketball/player/news/_/id/18247/marquise-kately",
"text": "News"
},
{
"href": "http://www.espn.com/mens-college-basketball/player/bio/_/id/18247/marquise-kately",
"text": "Bio"
},
{
"href": "http://www.espn.com/mens-college-basketball/player/_/id/18247/marquise-kately",
"text": "Overview"
}
],
"id": "18247",
"position": {
"displayName": "Forward",
"name": "Forward",
"abbreviation": "F"
},
"shortName": "M. Kately"
},
"ejected": false,
"stats": [
"37",
"2-9",
"0-0",
"0-2",
"0",
"3",
"3",
"4",
"0",
"2",
"0",
"2",
"4"
],
"didNotPlay": false,
"active": false
},
{
"starter": false,
"athlete": {
"uid": "s:40~l:41~a:16207",
"displayName": "Karanvir Aujla",
"jersey": "23 ",
"guid": "3a659b3ef611180e3aea6e7c6f34d13a",
"links": [
{
"href": "https://www.espn.com/mens-college-basketball/player/_/id/16207/karanvir-aujla",
"text": "Player Card"
},
{
"href": "http://www.espn.com/mens-college-basketball/player/stats/_/id/16207/karanvir-aujla",
"text": "Stats"
},
{
"href": "http://www.espn.com/mens-college-basketball/player/splits/_/id/16207/karanvir-aujla",
"text": "Splits"
},
{
"href": "http://www.espn.com/mens-college-basketball/player/gamelog/_/id/16207/karanvir-aujla",
"text": "Game Log"
},
{
"href": "http://www.espn.com/mens-college-basketball/player/news/_/id/16207/karanvir-aujla",
"text": "News"
},
{
"href": "http://www.espn.com/mens-college-basketball/player/bio/_/id/16207/karanvir-aujla",
"text": "Bio"
},
{
"href": "http://www.espn.com/mens-college-basketball/player/_/id/16207/karanvir-aujla",
"text": "Overview"
}
],
"id": "16207",
"position": {
"displayName": "Forward",
"name": "Forward",
"abbreviation": "F"
},
"shortName": "K. Aujla"
},
"ejected": false,
"stats": [
"4",
"0-0",
"0-0",
"0-0",
"0",
"0",
"0",
"0",
"0",
"0",
"0",
"1",
"0"
],
"didNotPlay": false,
"active": false
},
{
"starter": false,
"athlete": {
"uid": "s:40~l:41~a:15520",
"displayName": "Boubacar Coly",
"jersey": "4  ",
"guid": "0de80a1e45ef741dd5ff28942c2eac9f",
"links": [
{
"href": "https://www.espn.com/mens-college-basketball/player/_/id/15520/boubacar-coly",
"text": "Player Card"
},
{
"href": "http://www.espn.com/mens-college-basketball/player/stats/_/id/15520/boubacar-coly",
"text": "Stats"
},
{
"href": "http://www.espn.com/mens-college-basketball/player/splits/_/id/15520/boubacar-coly",
"text": "Splits"
},
{
"href": "http://www.espn.com/mens-college-basketball/player/gamelog/_/id/15520/boubacar-coly",
"text": "Game Log"
},
{
"href": "http://www.espn.com/mens-college-basketball/player/news/_/id/15520/boubacar-coly",
"text": "News"
},
{
"href": "http://www.espn.com/mens-college-basketball/player/bio/_/id/15520/boubacar-coly",
"text": "Bio"
},
{
"href": "http://www.espn.com/mens-college-basketball/player/_/id/15520/boubacar-coly",
"text": "Overview"
}
],
"id": "15520",
"position": {
"displayName": "Forward",
"name": "Forward",
"abbreviation": "F"
},
"shortName": "B. Coly"
},
"ejected": false,
"stats": [
"37",
"4-4",
"0-0",
"0-2",
"0",
"9",
"9",
"1",
"1",
"2",
"3",
"2",
"8"
],
"didNotPlay": false,
"active": false
},
{
"starter": false,
"athlete": {
"uid": "s:40~l:41~a:32478",
"displayName": "Rodney Stokes",
"jersey": "42 ",
"guid": "aa603d229e15f3409a589af3a3b30fab",
"links": [
{
"href": "https://www.espn.com/mens-college-basketball/player/_/id/32478/rodney-stokes",
"text": "Player Card"
},
{
"href": "http://www.espn.com/mens-college-basketball/player/stats/_/id/32478/rodney-stokes",
"text": "Stats"
},
{
"href": "http://www.espn.com/mens-college-basketball/player/splits/_/id/32478/rodney-stokes",
"text": "Splits"
},
{
"href": "http://www.espn.com/mens-college-basketball/player/gamelog/_/id/32478/rodney-stokes",
"text": "Game Log"
},
{
"href": "http://www.espn.com/mens-college-basketball/player/news/_/id/32478/rodney-stokes",
"text": "News"
},
{
"href": "http://www.espn.com/mens-college-basketball/player/bio/_/id/32478/rodney-stokes",
"text": "Bio"
},
{
"href": "http://www.espn.com/mens-college-basketball/player/_/id/32478/rodney-stokes",
"text": "Overview"
}
],
"id": "32478",
"position": {
"displayName": "Forward/Center",
"name": "Forward/Center",
"abbreviation": "F-C"
},
"shortName": "R. Stokes"
},
"ejected": false,
"stats": [
"11",
"0-1",
"0-0",
"0-0",
"0",
"2",
"2",
"1",
"1",
"2",
"0",
"1",
"0"
],
"didNotPlay": false,
"active": false
},
{
"starter": false,
"athlete": {
"uid": "s:40~l:41~a:32477",
"displayName": "Jamar Smith",
"jersey": "34 ",
"guid": "6ca8ecded61d142143d715de66b03fa3",
"links": [
{
"href": "https://www.espn.com/mens-college-basketball/player/_/id/32477/jamar-smith",
"text": "Player Card"
},
{
"href": "http://www.espn.com/mens-college-basketball/player/stats/_/id/32477/jamar-smith",
"text": "Stats"
},
{
"href": "http://www.espn.com/mens-college-basketball/player/splits/_/id/32477/jamar-smith",
"text": "Splits"
},
{
"href": "http://www.espn.com/mens-college-basketball/player/gamelog/_/id/32477/jamar-smith",
"text": "Game Log"
},
{
"href": "http://www.espn.com/mens-college-basketball/player/news/_/id/32477/jamar-smith",
"text": "News"
},
{
"href": "http://www.espn.com/mens-college-basketball/player/bio/_/id/32477/jamar-smith",
"text": "Bio"
},
{
"href": "http://www.espn.com/mens-college-basketball/player/_/id/32477/jamar-smith",
"text": "Overview"
}
],
"id": "32477",
"position": {
"displayName": "Guard",
"name": "Guard",
"abbreviation": "G"
},
"shortName": "J. Smith"
},
"ejected": false,
"stats": [
"33",
"5-12",
"0-2",
"6-8",
"1",
"2",
"3",
"0",
"0",
"3",
"2",
"2",
"16"
],
"didNotPlay": false,
"active": false
},
{
"starter": false,
"athlete": {
"uid": "s:40~l:41~a:32475",
"displayName": "Reggie Holmes",
"jersey": "11 ",
"guid": "930756fd09b301c15ca09ae14ca83484",
"links": [
{
"href": "https://www.espn.com/mens-college-basketball/player/_/id/32475/reggie-holmes",
"text": "Player Card"
},
{
"href": "http://www.espn.com/mens-college-basketball/player/stats/_/id/32475/reggie-holmes",
"text": "Stats"
},
{
"href": "http://www.espn.com/mens-college-basketball/player/splits/_/id/32475/reggie-holmes",
"text": "Splits"
},
{
"href": "http://www.espn.com/mens-college-basketball/player/gamelog/_/id/32475/reggie-holmes",
"text": "Game Log"
},
{
"href": "http://www.espn.com/mens-college-basketball/player/news/_/id/32475/reggie-holmes",
"text": "News"
},
{
"href": "http://www.espn.com/mens-college-basketball/player/bio/_/id/32475/reggie-holmes",
"text": "Bio"
},
{
"href": "http://www.espn.com/mens-college-basketball/player/_/id/32475/reggie-holmes",
"text": "Overview"
}
],
"id": "32475",
"position": {
"displayName": "Guard",
"name": "Guard",
"abbreviation": "G"
},
"shortName": "R. Holmes"
},
"ejected": false,
"stats": [
"27",
"5-11",
"3-6",
"3-4",
"3",
"3",
"6",
"0",
"0",
"1",
"2",
"2",
"16"
],
"didNotPlay": false,
"active": false
},
{
"starter": false,
"athlete": {
"uid": "s:40~l:41~a:32473",
"displayName": "Jerrell Green",
"jersey": "1  ",
"guid": "882d829f26e5d6886a213451369ee9d4",
"links": [
{
"href": "https://www.espn.com/mens-college-basketball/player/_/id/32473/jerrell-green",
"text": "Player Card"
},
{
"href": "http://www.espn.com/mens-college-basketball/player/stats/_/id/32473/jerrell-green",
"text": "Stats"
},
{
"href": "http://www.espn.com/mens-college-basketball/player/splits/_/id/32473/jerrell-green",
"text": "Splits"
},
{
"href": "http://www.espn.com/mens-college-basketball/player/gamelog/_/id/32473/jerrell-green",
"text": "Game Log"
},
{
"href": "http://www.espn.com/mens-college-basketball/player/news/_/id/32473/jerrell-green",
"text": "News"
},
{
"href": "http://www.espn.com/mens-college-basketball/player/bio/_/id/32473/jerrell-green",
"text": "Bio"
},
{
"href": "http://www.espn.com/mens-college-basketball/player/_/id/32473/jerrell-green",
"text": "Overview"
}
],
"id": "32473",
"position": {
"displayName": "Guard",
"name": "Guard",
"abbreviation": "G"
},
"shortName": "J. Green"
},
"ejected": false,
"stats": [
"28",
"4-7",
"1-1",
"1-2",
"1",
"3",
"4",
"3",
"1",
"0",
"3",
"3",
"10"
],
"didNotPlay": false,
"active": false
},
{
"starter": false,
"athlete": {
"uid": "s:40~l:41~a:36992",
"displayName": "Gene Johnson",
"jersey": "2  ",
"guid": "37f6f513e4c7b63e6699bbabca1ab719",
"links": [
{
"href": "https://www.espn.com/mens-college-basketball/player/_/id/36992/gene-johnson",
"text": "Player Card"
},
{
"href": "http://www.espn.com/mens-college-basketball/player/stats/_/id/36992/gene-johnson",
"text": "Stats"
},
{
"href": "http://www.espn.com/mens-college-basketball/player/splits/_/id/36992/gene-johnson",
"text": "Splits"
},
{
"href": "http://www.espn.com/mens-college-basketball/player/gamelog/_/id/36992/gene-johnson",
"text": "Game Log"
},
{
"href": "http://www.espn.com/mens-college-basketball/player/news/_/id/36992/gene-johnson",
"text": "News"
},
{
"href": "http://www.espn.com/mens-college-basketball/player/bio/_/id/36992/gene-johnson",
"text": "Bio"
},
{
"href": "http://www.espn.com/mens-college-basketball/player/_/id/36992/gene-johnson",
"text": "Overview"
}
],
"id": "36992",
"position": {
"displayName": "Forward",
"name": "Forward",
"abbreviation": "F"
},
"shortName": "G. Johnson"
},
"ejected": false,
"stats": [],
"didNotPlay": true,
"active": false
},
{
"starter": false,
"athlete": {
"uid": "s:40~l:41~a:40519",
"displayName": "Domonique Scott",
"guid": "5ff97d2d02a1d301952adc91f2cac159",
"links": [
{
"href": "https://www.espn.com/mens-college-basketball/player/_/id/40519/domonique-scott",
"text": "Player Card"
},
{
"href": "http://www.espn.com/mens-college-basketball/player/splits/_/id/40519/domonique-scott",
"text": "Splits"
},
{
"href": "http://www.espn.com/mens-college-basketball/player/gamelog/_/id/40519/domonique-scott",
"text": "Game Log"
},
{
"href": "http://www.espn.com/mens-college-basketball/player/news/_/id/40519/domonique-scott",
"text": "News"
},
{
"href": "http://www.espn.com/mens-college-basketball/player/bio/_/id/40519/domonique-scott",
"text": "Bio"
},
{
"href": "http://www.espn.com/mens-college-basketball/player/_/id/40519/domonique-scott",
"text": "Overview"
}
],
"id": "40519",
"position": {
"displayName": "Guard",
"name": "Guard",
"abbreviation": "G"
},
"shortName": "D. Scott"
},
"ejected": false,
"stats": [],
"didNotPlay": true,
"active": false
},
{
"starter": false,
"athlete": {
"uid": "s:40~l:41~a:36993",
"displayName": "Jermaine Bolden",
"jersey": "3  ",
"guid": "af9807be2f2a4ad8213dc318b2fb12b3",
"links": [
{
"href": "https://www.espn.com/mens-college-basketball/player/_/id/36993/jermaine-bolden",
"text": "Player Card"
},
{
"href": "http://www.espn.com/mens-college-basketball/player/stats/_/id/36993/jermaine-bolden",
"text": "Stats"
},
{
"href": "http://www.espn.com/mens-college-basketball/player/splits/_/id/36993/jermaine-bolden",
"text": "Splits"
},
{
"href": "http://www.espn.com/mens-college-basketball/player/gamelog/_/id/36993/jermaine-bolden",
"text": "Game Log"
},
{
"href": "http://www.espn.com/mens-college-basketball/player/news/_/id/36993/jermaine-bolden",
"text": "News"
},
{
"href": "http://www.espn.com/mens-college-basketball/player/bio/_/id/36993/jermaine-bolden",
"text": "Bio"
},
{
"href": "http://www.espn.com/mens-college-basketball/player/_/id/36993/jermaine-bolden",
"text": "Overview"
}
],
"id": "36993",
"position": {
"displayName": "Guard",
"name": "Guard",
"abbreviation": "G"
},
"shortName": "J. Bolden"
},
"ejected": false,
"stats": [],
"didNotPlay": true,
"active": false
},
{
"starter": false,
"athlete": {
"uid": "s:40~l:41~a:29741",
"displayName": "Rogers Barnes",
"jersey": "21 ",
"guid": "715febda6c33e3c459e6e2b885c06fdb",
"links": [
{
"href": "https://www.espn.com/mens-college-basketball/player/_/id/29741/rogers-barnes",
"text": "Player Card"
},
{
"href": "http://www.espn.com/mens-college-basketball/player/stats/_/id/29741/rogers-barnes",
"text": "Stats"
},
{
"href": "http://www.espn.com/mens-college-basketball/player/splits/_/id/29741/rogers-barnes",
"text": "Splits"
},
{
"href": "http://www.espn.com/mens-college-basketball/player/gamelog/_/id/29741/rogers-barnes",
"text": "Game Log"
},
{
"href": "http://www.espn.com/mens-college-basketball/player/news/_/id/29741/rogers-barnes",
"text": "News"
},
{
"href": "http://www.espn.com/mens-college-basketball/player/bio/_/id/29741/rogers-barnes",
"text": "Bio"
},
{
"href": "http://www.espn.com/mens-college-basketball/player/_/id/29741/rogers-barnes",
"text": "Overview"
}
],
"id": "29741",
"position": {
"displayName": "Guard",
"name": "Guard",
"abbreviation": "G"
},
"shortName": "R. Barnes"
},
"ejected": false,
"stats": [],
"didNotPlay": true,
"active": false
},
{
"starter": false,
"athlete": {
"uid": "s:40~l:41~a:40899",
"displayName": "Mike Cavanaugh",
"jersey": "5  ",
"guid": "2a901e769611fd15195c385008e9dd1f",
"links": [
{
"href": "https://www.espn.com/mens-college-basketball/player/_/id/40899/mike-cavanaugh",
"text": "Player Card"
},
{
"href": "http://www.espn.com/mens-college-basketball/player/splits/_/id/40899/mike-cavanaugh",
"text": "Splits"
},
{
"href": "http://www.espn.com/mens-college-basketball/player/gamelog/_/id/40899/mike-cavanaugh",
"text": "Game Log"
},
{
"href": "http://www.espn.com/mens-college-basketball/player/news/_/id/40899/mike-cavanaugh",
"text": "News"
},
{
"href": "http://www.espn.com/mens-college-basketball/player/bio/_/id/40899/mike-cavanaugh",
"text": "Bio"
},
{
"href": "http://www.espn.com/mens-college-basketball/player/_/id/40899/mike-cavanaugh",
"text": "Overview"
}
],
"id": "40899",
"position": {
"displayName": "Not Available",
"name": "Not Available",
"abbreviation": "NA"
},
"shortName": "M. Cavanaugh"
},
"ejected": false,
"stats": [],
"didNotPlay": true,
"active": false
}
],
"totals": [
"",
"24-48",
"4-9",
"10-18",
"8",
"27",
"35",
"9",
"3",
"12",
"11",
"16",
"62"
],
"descriptions": [
"Minutes",
"Field Goals Made/Attempted",
"3-Point Field Goals Made/Attempted",
"Free Throws Made/Attempted",
"Offensive Rebounds",
"Defensive Rebounds",
"Rebounds",
"Assists",
"Steals",
"Blocks",
"Turnovers",
"Personal Fouls",
"Points"
],
"labels": [
"MIN",
"FG",
"3PT",
"FT",
"OREB",
"DREB",
"REB",
"AST",
"STL",
"BLK",
"TO",
"PF",
"PTS"
]
}
]
}
]
},
"header": {
"uid": "s:40~l:41~e:273242415",
"week": 3,
"timeValid": true,
"league": {
"uid": "s:40~l:41",
"midsizeName": "NCAAM Basketball",
"name": "NCAA Men's Basketball",
"links": [
{
"rel": [
"index",
"desktop",
"league"
],
"href": "https://www.espn.com/mens-college-basketball/",
"text": "Index"
},
{
"rel": [
"index",
"sportscenter",
"app",
"league"
],
"href": "sportscenter://x-callback-url/showClubhouse?uid=s:40~l:41",
"text": "Index"
},
{
"rel": [
"schedule",
"desktop",
"league"
],
"href": "https://www.espn.com/mens-college-basketball/schedule",
"text": "Schedule"
},
{
"rel": [
"schedule",
"sportscenter",
"app",
"league"
],
"href": "sportscenter://x-callback-url/showClubhouse?uid=s:40~l:41&section=scores",
"text": "Schedule"
},
{
"rel": [
"standings",
"desktop",
"league"
],
"href": "http://www.espn.com/mens-college-basketball/standings",
"text": "Standings"
},
{
"rel": [
"standings",
"sportscenter",
"app",
"league"
],
"href": "sportscenter://x-callback-url/showClubhouse?uid=s:40~l:41&section=standings",
"text": "Standings"
},
{
"rel": [
"rankings",
"desktop",
"league"
],
"href": "https://www.espn.com/mens-college-basketball/rankings",
"text": "Rankings"
},
{
"rel": [
"scores",
"desktop",
"league"
],
"href": "http://www.espn.com/mens-college-basketball/scoreboard",
"text": "Scores"
},
{
"rel": [
"scores",
"sportscenter",
"app",
"league"
],
"href": "sportscenter://x-callback-url/showClubhouse?uid=s:40~l:41&section=scores",
"text": "Scores"
},
{
"rel": [
"stats",
"desktop",
"league"
],
"href": "http://www.espn.com/mens-college-basketball/statistics",
"text": "Stats"
},
{
"rel": [
"teams",
"desktop",
"league"
],
"href": "http://www.espn.com/mens-college-basketball/teams",
"text": "Teams"
},
{
"rel": [
"athletes",
"desktop",
"league"
],
"href": "http://www.espn.com/mens-college-basketball/players",
"text": "Players"
},
{
"rel": [
"injuries",
"desktop",
"league"
],
"href": "https://www.espn.com/mens-college-basketball/injuries",
"text": "Injuries"
},
{
"rel": [
"bpi_overview",
"desktop",
"league"
],
"href": "http://www.espn.com/mens-college-basketball/bpi",
"text": "Overview"
},
{
"rel": [
"bpi_bpi",
"desktop",
"league"
],
"href": "http://www.espn.com/mens-college-basketball/bpi/_/view/bpi",
"text": "BPI"
},
{
"rel": [
"bpi_resume",
"desktop",
"league"
],
"href": "http://www.espn.com/mens-college-basketball/bpi/_/view/resume",
"text": "Resume"
},
{
"rel": [
"bpi_projections",
"desktop",
"league"
],
"href": "http://www.espn.com/mens-college-basketball/bpi/_/view/projections",
"text": "Projections"
},
{
"rel": [
"bpi_predictions",
"desktop",
"league"
],
"href": "http://www.espn.com/mens-college-basketball/bpi/_/view/predictions",
"text": "Daily Predictions"
},
{
"rel": [
"bpi_tournament",
"desktop",
"league"
],
"href": "http://www.espn.com/mens-college-basketball/bpi/_/view/tournament",
"text": "Tournament"
}
],
"id": "41",
"abbreviation": "NCAAM",
"slug": "mens-college-basketball",
"isTournament": false
},
"competitions": [
{
"date": "2007-11-21T00:00Z",
"commentaryAvailable": false,
"conferenceCompetition": false,
"liveAvailable": false,
"broadcasts": [],
"playByPlaySource": "none",
"uid": "s:40~l:41~e:273242415~c:273242415",
"competitors": [
{
"uid": "s:40~l:41~t:2415",
"homeAway": "home",
"score": "62",
"winner": true,
"record": [
{
"summary": "3-1",
"displayValue": "3-1",
"type": "total"
},
{
"summary": "1-0",
"displayValue": "1-0",
"type": "home"
},
{
"summary": "0-0",
"displayValue": "0-0",
"type": "vsconf"
}
],
"possession": false,
"id": "2415",
"team": {
"uid": "s:40~l:41~t:2415",
"alternateColor": "f47937",
"color": "014786",
"displayName": "Morgan St Bears",
"name": "Bears",
"nickname": "Morgan State",
"location": "Morgan St",
"links": [
{
"rel": [
"clubhouse",
"desktop",
"team"
],
"href": "https://www.espn.com/mens-college-basketball/team/_/id/2415/morgan-st-bears",
"text": "Clubhouse"
}
],
"id": "2415",
"abbreviation": "MORG",
"logos": [
{
"width": 500,
"alt": "",
"rel": [
"full",
"default"
],
"href": "https://a.espncdn.com/i/teamlogos/ncaa/500/2415.png",
"height": 500
},
{
"width": 500,
"alt": "",
"rel": [
"full",
"dark"
],
"href": "https://a.espncdn.com/i/teamlogos/ncaa/500-dark/2415.png",
"height": 500
}
]
},
"linescores": [
{
"displayValue": "25"
},
{
"displayValue": "37"
}
],
"order": 0
},
{
"uid": "s:40~l:41~t:44",
"homeAway": "away",
"score": "54",
"winner": false,
"record": [
{
"summary": "2-3",
"displayValue": "2-3",
"type": "total"
},
{
"summary": "1-2",
"displayValue": "1-2",
"type": "road"
},
{
"summary": "0-0",
"displayValue": "0-0",
"type": "vsconf"
}
],
"possession": false,
"id": "44",
"team": {
"uid": "s:40~l:41~t:44",
"alternateColor": "c8102e",
"color": "c41130",
"displayName": "American Eagles",
"name": "Eagles",
"nickname": "American",
"location": "American",
"links": [
{
"rel": [
"clubhouse",
"desktop",
"team"
],
"href": "https://www.espn.com/mens-college-basketball/team/_/id/44/american-eagles",
"text": "Clubhouse"
}
],
"id": "44",
"abbreviation": "AMER",
"logos": [
{
"width": 500,
"alt": "",
"rel": [
"full",
"default"
],
"href": "https://a.espncdn.com/i/teamlogos/ncaa/500/44.png",
"height": 500
},
{
"width": 500,
"alt": "",
"rel": [
"full",
"dark"
],
"href": "https://a.espncdn.com/i/teamlogos/ncaa/500-dark/44.png",
"height": 500
}
]
},
"linescores": [
{
"displayValue": "23"
},
{
"displayValue": "31"
}
],
"order": 1
}
],
"onWatchESPN": false,
"boxscoreAvailable": true,
"id": "273242415",
"shotChartAvailable": false,
"timeoutsAvailable": false,
"neutralSite": false,
"recent": false,
"boxscoreSource": "full",
"possessionArrowAvailable": false,
"status": {
"type": {
"name": "STATUS_FINAL",
"description": "Final",
"id": "3",
"state": "post",
"completed": true,
"detail": "Final",
"shortDetail": "Final"
}
}
}
],
"season": {
"year": 2008,
"type": 2
},
"links": [
{
"isExternal": false,
"shortText": "Summary",
"rel": [
"summary",
"desktop",
"event"
],
"href": "http://www.espn.com/mens-college-basketball/game/_/gameId/273242415",
"text": "Gamecast",
"isPremium": false
},
{
"isExternal": false,
"shortText": "Box Score",
"rel": [
"boxscore",
"desktop",
"event"
],
"href": "http://www.espn.com/mens-college-basketball/boxscore/_/gameId/273242415",
"text": "Box Score",
"isPremium": false
},
{
"isExternal": false,
"shortText": "Team Stats",
"rel": [
"teamstats",
"desktop",
"event"
],
"href": "https://www.espn.com/mens-college-basketball/matchup?gameId=273242415",
"text": "Team Stats",
"isPremium": false
}
],
"id": "273242415"
},
"broadcasts": [],
"videos": [],
"playByPlaySource": "none",
"standings": {
"fullViewLink": {
"text": "Full Standings",
"href": "http://www.espn.com/mens-college-basketball/standings"
},
"groups": [
{
"header": "2020-2021 Patriot League Standings",
"href": "https://www.espn.com/mens-college-basketball/standings/_/group/22",
"divisions": [
{
"header": "Central",
"href": "https://www.espn.com/mens-college-basketball/standings/_/group/69",
"standings": {
"entries": [
{
"uid": "s:40~l:41~t:322",
"stats": [
{
"shortDisplayName": "Season",
"summary": "9-6",
"displayValue": "9-6",
"displayName": "Team Season Record",
"name": "Season",
"description": "Overall Record",
"id": "0",
"abbreviation": "Season",
"type": "total"
},
{
"shortDisplayName": "GB",
"displayValue": "-",
"displayName": "Games Back",
"name": "gamesBehind",
"description": "Games Back",
"abbreviation": "GB",
"type": "vsconf_gamesbehind",
"value": 0
},
{
"shortDisplayName": "CONF",
"summary": "9-5",
"displayValue": "9-5",
"displayName": "CONF",
"name": "vs Conference",
"description": "Conference Record",
"id": "9",
"abbreviation": "VS CONF",
"type": "vsconf"
}
],
"link": "https://www.espn.com/mens-college-basketball/team/_/id/322/lafayette-leopards",
"logo": [
{
"width": 500,
"alt": "",
"rel": [
"full",
"default"
],
"href": "https://a.espncdn.com/i/teamlogos/ncaa/500/322.png",
"height": 500
}
],
"team": "Lafayette",
"id": "322"
},
{
"uid": "s:40~l:41~t:2083",
"stats": [
{
"shortDisplayName": "Season",
"summary": "5-7",
"displayValue": "5-7",
"displayName": "Team Season Record",
"name": "Season",
"description": "Overall Record",
"id": "0",
"abbreviation": "Season",
"type": "total"
},
{
"shortDisplayName": "GB",
"displayValue": "3",
"displayName": "Games Back",
"name": "gamesBehind",
"description": "Games Back",
"abbreviation": "GB",
"type": "vsconf_gamesbehind",
"value": 3
},
{
"shortDisplayName": "CONF",
"summary": "4-6",
"displayValue": "4-6",
"displayName": "CONF",
"name": "vs Conference",
"description": "Conference Record",
"id": "9",
"abbreviation": "VS CONF",
"type": "vsconf"
}
],
"link": "https://www.espn.com/mens-college-basketball/team/_/id/2083/bucknell-bison",
"logo": [
{
"width": 500,
"alt": "",
"rel": [
"full",
"default"
],
"href": "https://a.espncdn.com/i/teamlogos/ncaa/500/2083.png",
"height": 500
}
],
"team": "Bucknell",
"id": "2083"
},
{
"uid": "s:40~l:41~t:2329",
"stats": [
{
"shortDisplayName": "Season",
"summary": "4-11",
"displayValue": "4-11",
"displayName": "Team Season Record",
"name": "Season",
"description": "Overall Record",
"id": "0",
"abbreviation": "Season",
"type": "total"
},
{
"shortDisplayName": "GB",
"displayValue": "5",
"displayName": "Games Back",
"name": "gamesBehind",
"description": "Games Back",
"abbreviation": "GB",
"type": "vsconf_gamesbehind",
"value": 5
},
{
"shortDisplayName": "CONF",
"summary": "4-10",
"displayValue": "4-10",
"displayName": "CONF",
"name": "vs Conference",
"description": "Conference Record",
"id": "9",
"abbreviation": "VS CONF",
"type": "vsconf"
}
],
"link": "https://www.espn.com/mens-college-basketball/team/_/id/2329/lehigh-mountain-hawks",
"logo": [
{
"width": 500,
"alt": "",
"rel": [
"full",
"default"
],
"href": "https://a.espncdn.com/i/teamlogos/ncaa/500/2329.png",
"height": 500
}
],
"team": "Lehigh",
"id": "2329"
}
]
}
},
{
"header": "North",
"href": "https://www.espn.com/mens-college-basketball/standings/_/group/70",
"standings": {
"entries": [
{
"uid": "s:40~l:41~t:2142",
"stats": [
{
"shortDisplayName": "Season",
"summary": "14-2",
"displayValue": "14-2",
"displayName": "Team Season Record",
"name": "Season",
"description": "Overall Record",
"id": "0",
"abbreviation": "Season",
"type": "total"
},
{
"shortDisplayName": "GB",
"displayValue": "-",
"displayName": "Games Back",
"name": "gamesBehind",
"description": "Games Back",
"abbreviation": "GB",
"type": "vsconf_gamesbehind",
"value": 0
},
{
"shortDisplayName": "CONF",
"summary": "11-1",
"displayValue": "11-1",
"displayName": "CONF",
"name": "vs Conference",
"description": "Conference Record",
"id": "9",
"abbreviation": "VS CONF",
"type": "vsconf"
}
],
"link": "https://www.espn.com/mens-college-basketball/team/_/id/2142/colgate-raiders",
"logo": [
{
"width": 500,
"alt": "",
"rel": [
"full",
"default"
],
"href": "https://a.espncdn.com/i/teamlogos/ncaa/500/2142.png",
"height": 500
}
],
"team": "Colgate",
"id": "2142"
},
{
"uid": "s:40~l:41~t:349",
"stats": [
{
"shortDisplayName": "Season",
"summary": "12-10",
"displayValue": "12-10",
"displayName": "Team Season Record",
"name": "Season",
"description": "Overall Record",
"id": "0",
"abbreviation": "Season",
"type": "total"
},
{
"shortDisplayName": "GB",
"displayValue": "5",
"displayName": "Games Back",
"name": "gamesBehind",
"description": "Games Back",
"abbreviation": "GB",
"type": "vsconf_gamesbehind",
"value": 5
},
{
"shortDisplayName": "CONF",
"summary": "7-7",
"displayValue": "7-7",
"displayName": "CONF",
"name": "vs Conference",
"description": "Conference Record",
"id": "9",
"abbreviation": "VS CONF",
"type": "vsconf"
}
],
"link": "https://www.espn.com/mens-college-basketball/team/_/id/349/army-black-knights",
"logo": [
{
"width": 500,
"alt": "",
"rel": [
"full",
"default"
],
"href": "https://a.espncdn.com/i/teamlogos/ncaa/500/349.png",
"height": 500
}
],
"team": "Army",
"id": "349"
},
{
"uid": "s:40~l:41~t:104",
"stats": [
{
"shortDisplayName": "Season",
"summary": "7-11",
"displayValue": "7-11",
"displayName": "Team Season Record",
"name": "Season",
"description": "Overall Record",
"id": "0",
"abbreviation": "Season",
"type": "total"
},
{
"shortDisplayName": "GB",
"displayValue": "7",
"displayName": "Games Back",
"name": "gamesBehind",
"description": "Games Back",
"abbreviation": "GB",
"type": "vsconf_gamesbehind",
"value": 7
},
{
"shortDisplayName": "CONF",
"summary": "6-10",
"displayValue": "6-10",
"displayName": "CONF",
"name": "vs Conference",
"description": "Conference Record",
"id": "9",
"abbreviation": "VS CONF",
"type": "vsconf"
}
],
"link": "https://www.espn.com/mens-college-basketball/team/_/id/104/boston-university-terriers",
"logo": [
{
"width": 500,
"alt": "",
"rel": [
"full",
"default"
],
"href": "https://a.espncdn.com/i/teamlogos/ncaa/500/104.png",
"height": 500
}
],
"team": "Boston University",
"id": "104"
},
{
"uid": "s:40~l:41~t:107",
"stats": [
{
"shortDisplayName": "Season",
"summary": "5-11",
"displayValue": "5-11",
"displayName": "Team Season Record",
"name": "Season",
"description": "Overall Record",
"id": "0",
"abbreviation": "Season",
"type": "total"
},
{
"shortDisplayName": "GB",
"displayValue": "8",
"displayName": "Games Back",
"name": "gamesBehind",
"description": "Games Back",
"abbreviation": "GB",
"type": "vsconf_gamesbehind",
"value": 8
},
{
"shortDisplayName": "CONF",
"summary": "5-11",
"displayValue": "5-11",
"displayName": "CONF",
"name": "vs Conference",
"description": "Conference Record",
"id": "9",
"abbreviation": "VS CONF",
"type": "vsconf"
}
],
"link": "https://www.espn.com/mens-college-basketball/team/_/id/107/holy-cross-crusaders",
"logo": [
{
"width": 500,
"alt": "",
"rel": [
"full",
"default"
],
"href": "https://a.espncdn.com/i/teamlogos/ncaa/500/107.png",
"height": 500
}
],
"team": "Holy Cross",
"id": "107"
}
]
}
},
{
"header": "Patriot League - South",
"href": "https://www.espn.com/mens-college-basketball/standings/_/group/71",
"standings": {
"entries": [
{
"uid": "s:40~l:41~t:2426",
"stats": [
{
"shortDisplayName": "Season",
"summary": "15-3",
"displayValue": "15-3",
"displayName": "Team Season Record",
"name": "Season",
"description": "Overall Record",
"id": "0",
"abbreviation": "Season",
"type": "total"
},
{
"shortDisplayName": "GB",
"displayValue": "-",
"displayName": "Games Back",
"name": "gamesBehind",
"description": "Games Back",
"abbreviation": "GB",
"type": "vsconf_gamesbehind",
"value": 0
},
{
"shortDisplayName": "CONF",
"summary": "12-1",
"displayValue": "12-1",
"displayName": "CONF",
"name": "vs Conference",
"description": "Conference Record",
"id": "9",
"abbreviation": "VS CONF",
"type": "vsconf"
}
],
"link": "https://www.espn.com/mens-college-basketball/team/_/id/2426/navy-midshipmen",
"logo": [
{
"width": 500,
"alt": "",
"rel": [
"full",
"default"
],
"href": "https://a.espncdn.com/i/teamlogos/ncaa/500/2426.png",
"height": 500
}
],
"team": "Navy",
"id": "2426"
},
{
"uid": "s:40~l:41~t:44",
"stats": [
{
"shortDisplayName": "Season",
"summary": "4-6",
"displayValue": "4-6",
"displayName": "Team Season Record",
"name": "Season",
"description": "Overall Record",
"id": "0",
"abbreviation": "Season",
"type": "total"
},
{
"shortDisplayName": "GB",
"displayValue": "6",
"displayName": "Games Back",
"name": "gamesBehind",
"description": "Games Back",
"abbreviation": "GB",
"type": "vsconf_gamesbehind",
"value": 6
},
{
"shortDisplayName": "CONF",
"summary": "4-5",
"displayValue": "4-5",
"displayName": "CONF",
"name": "vs Conference",
"description": "Conference Record",
"id": "9",
"abbreviation": "VS CONF",
"type": "vsconf"
}
],
"link": "https://www.espn.com/mens-college-basketball/team/_/id/44/american-eagles",
"logo": [
{
"width": 500,
"alt": "",
"rel": [
"full",
"default"
],
"href": "https://a.espncdn.com/i/teamlogos/ncaa/500/44.png",
"height": 500
}
],
"team": "American",
"id": "44"
},
{
"uid": "s:40~l:41~t:2352",
"stats": [
{
"shortDisplayName": "Season",
"summary": "6-11",
"displayValue": "6-11",
"displayName": "Team Season Record",
"name": "Season",
"description": "Overall Record",
"id": "0",
"abbreviation": "Season",
"type": "total"
},
{
"shortDisplayName": "GB",
"displayValue": "8.5",
"displayName": "Games Back",
"name": "gamesBehind",
"description": "Games Back",
"abbreviation": "GB",
"type": "vsconf_gamesbehind",
"value": 8.5
},
{
"shortDisplayName": "CONF",
"summary": "4-10",
"displayValue": "4-10",
"displayName": "CONF",
"name": "vs Conference",
"description": "Conference Record",
"id": "9",
"abbreviation": "VS CONF",
"type": "vsconf"
}
],
"link": "https://www.espn.com/mens-college-basketball/team/_/id/2352/loyola-md-greyhounds",
"logo": [
{
"width": 500,
"alt": "",
"rel": [
"full",
"default"
],
"href": "https://a.espncdn.com/i/teamlogos/ncaa/500/2352.png",
"height": 500
}
],
"team": "Loyola (MD)",
"id": "2352"
}
]
}
}
]
},
{
"header": "2020-2021 Mid-Eastern Athletic Conference Standings",
"href": "https://www.espn.com/mens-college-basketball/standings/_/group/16",
"divisions": [
{
"header": "Mid-Eastern Athletic - North",
"href": "https://www.espn.com/mens-college-basketball/standings/_/group/66",
"standings": {
"entries": [
{
"uid": "s:40~l:41~t:2450",
"stats": [
{
"shortDisplayName": "Season",
"summary": "17-8",
"displayValue": "17-8",
"displayName": "Team Season Record",
"name": "Season",
"description": "Overall Record",
"id": "0",
"abbreviation": "Season",
"type": "total"
},
{
"shortDisplayName": "GB",
"displayValue": "-",
"displayName": "Games Back",
"name": "gamesBehind",
"description": "Games Back",
"abbreviation": "GB",
"type": "vsconf_gamesbehind",
"value": 0
},
{
"shortDisplayName": "CONF",
"summary": "8-4",
"displayValue": "8-4",
"displayName": "CONF",
"name": "vs Conference",
"description": "Conference Record",
"id": "9",
"abbreviation": "VS CONF",
"type": "vsconf"
}
],
"link": "https://www.espn.com/mens-college-basketball/team/_/id/2450/norfolk-state-spartans",
"logo": [
{
"width": 500,
"alt": "",
"rel": [
"full",
"default"
],
"href": "https://a.espncdn.com/i/teamlogos/ncaa/500/2450.png",
"height": 500
}
],
"team": "Norfolk State",
"id": "2450"
},
{
"uid": "s:40~l:41~t:2154",
"stats": [
{
"shortDisplayName": "Season",
"summary": "9-13",
"displayValue": "9-13",
"displayName": "Team Season Record",
"name": "Season",
"description": "Overall Record",
"id": "0",
"abbreviation": "Season",
"type": "total"
},
{
"shortDisplayName": "GB",
"displayValue": "-",
"displayName": "Games Back",
"name": "gamesBehind",
"description": "Games Back",
"abbreviation": "GB",
"type": "vsconf_gamesbehind",
"value": 0
},
{
"shortDisplayName": "CONF",
"summary": "8-4",
"displayValue": "8-4",
"displayName": "CONF",
"name": "vs Conference",
"description": "Conference Record",
"id": "9",
"abbreviation": "VS CONF",
"type": "vsconf"
}
],
"link": "https://www.espn.com/mens-college-basketball/team/_/id/2154/coppin-state-eagles",
"logo": [
{
"width": 500,
"alt": "",
"rel": [
"full",
"default"
],
"href": "https://a.espncdn.com/i/teamlogos/ncaa/500/2154.png",
"height": 500
}
],
"team": "Coppin State",
"id": "2154"
},
{
"uid": "s:40~l:41~t:2415",
"stats": [
{
"shortDisplayName": "Season",
"summary": "14-8",
"displayValue": "14-8",
"displayName": "Team Season Record",
"name": "Season",
"description": "Overall Record",
"id": "0",
"abbreviation": "Season",
"type": "total"
},
{
"shortDisplayName": "GB",
"displayValue": "1",
"displayName": "Games Back",
"name": "gamesBehind",
"description": "Games Back",
"abbreviation": "GB",
"type": "vsconf_gamesbehind",
"value": 1
},
{
"shortDisplayName": "CONF",
"summary": "7-5",
"displayValue": "7-5",
"displayName": "CONF",
"name": "vs Conference",
"description": "Conference Record",
"id": "9",
"abbreviation": "VS CONF",
"type": "vsconf"
}
],
"link": "https://www.espn.com/mens-college-basketball/team/_/id/2415/morgan-st-bears",
"logo": [
{
"width": 500,
"alt": "",
"rel": [
"full",
"default"
],
"href": "https://a.espncdn.com/i/teamlogos/ncaa/500/2415.png",
"height": 500
}
],
"team": "Morgan St",
"id": "2415"
},
{
"uid": "s:40~l:41~t:2169",
"stats": [
{
"shortDisplayName": "Season",
"summary": "3-16",
"displayValue": "3-16",
"displayName": "Team Season Record",
"name": "Season",
"description": "Overall Record",
"id": "0",
"abbreviation": "Season",
"type": "total"
},
{
"shortDisplayName": "GB",
"displayValue": "7",
"displayName": "Games Back",
"name": "gamesBehind",
"description": "Games Back",
"abbreviation": "GB",
"type": "vsconf_gamesbehind",
"value": 7
},
{
"shortDisplayName": "CONF",
"summary": "1-11",
"displayValue": "1-11",
"displayName": "CONF",
"name": "vs Conference",
"description": "Conference Record",
"id": "9",
"abbreviation": "VS CONF",
"type": "vsconf"
}
],
"link": "https://www.espn.com/mens-college-basketball/team/_/id/2169/delaware-state-hornets",
"logo": [
{
"width": 500,
"alt": "",
"rel": [
"full",
"default"
],
"href": "https://a.espncdn.com/i/teamlogos/ncaa/500/2169.png",
"height": 500
}
],
"team": "Delaware State",
"id": "2169"
},
{
"uid": "s:40~l:41~t:47",
"stats": [
{
"shortDisplayName": "Season",
"summary": "1-4",
"displayValue": "1-4",
"displayName": "Team Season Record",
"name": "Season",
"description": "Overall Record",
"id": "0",
"abbreviation": "Season",
"type": "total"
},
{
"shortDisplayName": "GB",
"displayValue": "2",
"displayName": "Games Back",
"name": "gamesBehind",
"description": "Games Back",
"abbreviation": "GB",
"type": "vsconf_gamesbehind",
"value": 2
},
{
"shortDisplayName": "CONF",
"summary": "0-0",
"displayValue": "0-0",
"displayName": "CONF",
"name": "vs Conference",
"description": "Conference Record",
"id": "9",
"abbreviation": "VS CONF",
"type": "vsconf"
}
],
"link": "https://www.espn.com/mens-college-basketball/team/_/id/47/howard-bison",
"logo": [
{
"width": 500,
"alt": "",
"rel": [
"full",
"default"
],
"href": "https://a.espncdn.com/i/teamlogos/ncaa/500/47.png",
"height": 500
}
],
"team": "Howard",
"id": "47"
}
]
}
},
{
"header": "Mid-Eastern Athletic - South",
"href": "https://www.espn.com/mens-college-basketball/standings/_/group/67",
"standings": {
"entries": [
{
"uid": "s:40~l:41~t:2448",
"stats": [
{
"shortDisplayName": "Season",
"summary": "11-10",
"displayValue": "11-10",
"displayName": "Team Season Record",
"name": "Season",
"description": "Overall Record",
"id": "0",
"abbreviation": "Season",
"type": "total"
},
{
"shortDisplayName": "GB",
"displayValue": "-",
"displayName": "Games Back",
"name": "gamesBehind",
"description": "Games Back",
"abbreviation": "GB",
"type": "vsconf_gamesbehind",
"value": 0
},
{
"shortDisplayName": "CONF",
"summary": "7-1",
"displayValue": "7-1",
"displayName": "CONF",
"name": "vs Conference",
"description": "Conference Record",
"id": "9",
"abbreviation": "VS CONF",
"type": "vsconf"
}
],
"link": "https://www.espn.com/mens-college-basketball/team/_/id/2448/north-carolina-at-aggies",
"logo": [
{
"width": 500,
"alt": "",
"rel": [
"full",
"default"
],
"href": "https://a.espncdn.com/i/teamlogos/ncaa/500/2448.png",
"height": 500
}
],
"team": "North Carolina A&T",
"id": "2448"
},
{
"uid": "s:40~l:41~t:50",
"stats": [
{
"shortDisplayName": "Season",
"summary": "8-12",
"displayValue": "8-12",
"displayName": "Team Season Record",
"name": "Season",
"description": "Overall Record",
"id": "0",
"abbreviation": "Season",
"type": "total"
},
{
"shortDisplayName": "GB",
"displayValue": "2",
"displayName": "Games Back",
"name": "gamesBehind",
"description": "Games Back",
"abbreviation": "GB",
"type": "vsconf_gamesbehind",
"value": 2
},
{
"shortDisplayName": "CONF",
"summary": "7-5",
"displayValue": "7-5",
"displayName": "CONF",
"name": "vs Conference",
"description": "Conference Record",
"id": "9",
"abbreviation": "VS CONF",
"type": "vsconf"
}
],
"link": "https://www.espn.com/mens-college-basketball/team/_/id/50/florida-am-rattlers",
"logo": [
{
"width": 500,
"alt": "",
"rel": [
"full",
"default"
],
"href": "https://a.espncdn.com/i/teamlogos/ncaa/500/50.png",
"height": 500
}
],
"team": "Florida A&M",
"id": "50"
},
{
"uid": "s:40~l:41~t:2428",
"stats": [
{
"shortDisplayName": "Season",
"summary": "5-9",
"displayValue": "5-9",
"displayName": "Team Season Record",
"name": "Season",
"description": "Overall Record",
"id": "0",
"abbreviation": "Season",
"type": "total"
},
{
"shortDisplayName": "GB",
"displayValue": "4",
"displayName": "Games Back",
"name": "gamesBehind",
"description": "Games Back",
"abbreviation": "GB",
"type": "vsconf_gamesbehind",
"value": 4
},
{
"shortDisplayName": "CONF",
"summary": "3-5",
"displayValue": "3-5",
"displayName": "CONF",
"name": "vs Conference",
"description": "Conference Record",
"id": "9",
"abbreviation": "VS CONF",
"type": "vsconf"
}
],
"link": "https://www.espn.com/mens-college-basketball/team/_/id/2428/north-carolina-central-eagles",
"logo": [
{
"width": 500,
"alt": "",
"rel": [
"full",
"default"
],
"href": "https://a.espncdn.com/i/teamlogos/ncaa/500/2428.png",
"height": 500
}
],
"team": "North Carolina Central",
"id": "2428"
},
{
"uid": "s:40~l:41~t:2569",
"stats": [
{
"shortDisplayName": "Season",
"summary": "1-17",
"displayValue": "1-17",
"displayName": "Team Season Record",
"name": "Season",
"description": "Overall Record",
"id": "0",
"abbreviation": "Season",
"type": "total"
},
{
"shortDisplayName": "GB",
"displayValue": "6",
"displayName": "Games Back",
"name": "gamesBehind",
"description": "Games Back",
"abbreviation": "GB",
"type": "vsconf_gamesbehind",
"value": 6
},
{
"shortDisplayName": "CONF",
"summary": "1-7",
"displayValue": "1-7",
"displayName": "CONF",
"name": "vs Conference",
"description": "Conference Record",
"id": "9",
"abbreviation": "VS CONF",
"type": "vsconf"
}
],
"link": "https://www.espn.com/mens-college-basketball/team/_/id/2569/south-carolina-state-bulldogs",
"logo": [
{
"width": 500,
"alt": "",
"rel": [
"full",
"default"
],
"href": "https://a.espncdn.com/i/teamlogos/ncaa/500/2569.png",
"height": 500
}
],
"team": "South Carolina State",
"id": "2569"
}
]
}
}
]
}
]
},
"timeouts": {
"2415": {
"1": [],
"2": []
},
"44": {
"1": [],
"2": []
}
},
"pickcenter": [],
"againstTheSpread": [
{
"team": {
"id": "44",
"uid": "s:40~l:41~t:44",
"displayName": "American Eagles",
"abbreviation": "AMER",
"links": [
{
"href": "https://www.espn.com/mens-college-basketball/team/_/id/44/american-eagles",
"text": "Clubhouse"
},
{
"href": "https://www.espn.com/mens-college-basketball/team/schedule/_/id/44",
"text": "Schedule"
}
],
"logo": "https://a.espncdn.com/i/teamlogos/ncaa/500/44.png"
},
"records": []
},
{
"team": {
"id": "2415",
"uid": "s:40~l:41~t:2415",
"displayName": "Morgan St Bears",
"abbreviation": "MORG",
"links": [
{
"href": "https://www.espn.com/mens-college-basketball/team/_/id/2415/morgan-st-bears",
"text": "Clubhouse"
},
{
"href": "https://www.espn.com/mens-college-basketball/team/schedule/_/id/2415",
"text": "Schedule"
}
],
"logo": "https://a.espncdn.com/i/teamlogos/ncaa/500/2415.png"
},
"records": []
}
],
"odds": [],
"predictor": {
"header": "Matchup Predictor",
"homeTeam": {
"id": "2415",
"gameProjection": "53.7",
"teamChanceLoss": "46.3",
"teamChanceTie": "0.0"
},
"awayTeam": {
"id": "44",
"gameProjection": "46.3",
"teamChanceLoss": "53.7",
"teamChanceTie": "0.0"
}
},
"espnWP": [],
"gameInfo": {
"date": "2007-11-21T00:00Z",
"commentaryAvailable": false,
"conferenceCompetition": false,
"liveAvailable": false,
"broadcasts": [],
"playByPlaySource": "none",
"uid": "s:40~l:41~e:273242415~c:273242415",
"competitors": [
{
"uid": "s:40~l:41~t:2415",
"homeAway": "home",
"score": "62",
"winner": true,
"record": [
{
"summary": "3-1",
"displayValue": "3-1",
"type": "total"
},
{
"summary": "1-0",
"displayValue": "1-0",
"type": "home"
},
{
"summary": "0-0",
"displayValue": "0-0",
"type": "vsconf"
}
],
"possession": false,
"id": "2415",
"team": {
"uid": "s:40~l:41~t:2415",
"alternateColor": "f47937",
"color": "014786",
"displayName": "Morgan St Bears",
"name": "Bears",
"nickname": "Morgan State",
"location": "Morgan St",
"links": [
{
"rel": [
"clubhouse",
"desktop",
"team"
],
"href": "https://www.espn.com/mens-college-basketball/team/_/id/2415/morgan-st-bears",
"text": "Clubhouse"
}
],
"id": "2415",
"abbreviation": "MORG",
"logos": [
{
"width": 500,
"alt": "",
"rel": [
"full",
"default"
],
"href": "https://a.espncdn.com/i/teamlogos/ncaa/500/2415.png",
"height": 500
},
{
"width": 500,
"alt": "",
"rel": [
"full",
"dark"
],
"href": "https://a.espncdn.com/i/teamlogos/ncaa/500-dark/2415.png",
"height": 500
}
]
},
"linescores": [
{
"displayValue": "25"
},
{
"displayValue": "37"
}
],
"order": 0
},
{
"uid": "s:40~l:41~t:44",
"homeAway": "away",
"score": "54",
"winner": false,
"record": [
{
"summary": "2-3",
"displayValue": "2-3",
"type": "total"
},
{
"summary": "1-2",
"displayValue": "1-2",
"type": "road"
},
{
"summary": "0-0",
"displayValue": "0-0",
"type": "vsconf"
}
],
"possession": false,
"id": "44",
"team": {
"uid": "s:40~l:41~t:44",
"alternateColor": "c8102e",
"color": "c41130",
"displayName": "American Eagles",
"name": "Eagles",
"nickname": "American",
"location": "American",
"links": [
{
"rel": [
"clubhouse",
"desktop",
"team"
],
"href": "https://www.espn.com/mens-college-basketball/team/_/id/44/american-eagles",
"text": "Clubhouse"
}
],
"id": "44",
"abbreviation": "AMER",
"logos": [
{
"width": 500,
"alt": "",
"rel": [
"full",
"default"
],
"href": "https://a.espncdn.com/i/teamlogos/ncaa/500/44.png",
"height": 500
},
{
"width": 500,
"alt": "",
"rel": [
"full",
"dark"
],
"href": "https://a.espncdn.com/i/teamlogos/ncaa/500-dark/44.png",
"height": 500
}
]
},
"linescores": [
{
"displayValue": "23"
},
{
"displayValue": "31"
}
],
"order": 1
}
],
"onWatchESPN": false,
"boxscoreAvailable": true,
"id": "273242415",
"shotChartAvailable": false,
"timeoutsAvailable": false,
"neutralSite": false,
"recent": false,
"boxscoreSource": "full",
"possessionArrowAvailable": false,
"status": {
"type": {
"name": "STATUS_FINAL",
"description": "Final",
"id": "3",
"state": "post",
"completed": true,
"detail": "Final",
"shortDetail": "Final"
}
}
},
"season": {
"year": 2008,
"type": 2
}
}